CHANGES.txt
MANIFEST.in
README.txt
setup.py
src/erp5/__init__.py
src/erp5.recipe.testnode.egg-info/PKG-INFO
src/erp5.recipe.testnode.egg-info/SOURCES.txt
src/erp5.recipe.testnode.egg-info/dependency_links.txt
src/erp5.recipe.testnode.egg-info/entry_points.txt
src/erp5.recipe.testnode.egg-info/namespace_packages.txt
src/erp5.recipe.testnode.egg-info/requires.txt
src/erp5.recipe.testnode.egg-info/top_level.txt
src/erp5/recipe/__init__.py
src/erp5/recipe/testnode/SlapOSControler.py
src/erp5/recipe/testnode/Updater.py
src/erp5/recipe/testnode/__init__.py
src/erp5/recipe/testnode/testnode.py
src/erp5/recipe/testnode/template/slapos.cfg.in