Metadata-Version: 1.0
Name: erp5.recipe.testnode
Version: 1.0.12
Summary: ZC Buildout recipe for create an testnode instance
Home-page: UNKNOWN
Author: UNKNOWN
Author-email: UNKNOWN
License: GPLv3
Keywords: buildout erp5 test
Platform: UNKNOWN
Classifier: Framework :: Buildout :: Recipe
Classifier: Programming Language :: Python
